pypersonalizedutilitykit/__init__.py
pypersonalizedutilitykit/base_tool.py
pypersonalizedutilitykit/convert_file.py
pypersonalizedutilitykit/encrypt.py
pypersonalizedutilitykit/faker_util.py
pypersonalizedutilitykit/host_env.py
pypersonalizedutilitykit/hypothesis_data.py
pypersonalizedutilitykit/log.py
pypersonalizedutilitykit/login_base.py
pypersonalizedutilitykit/my_requests.py
pypersonalizedutilitykit/operation_cash.py
pypersonalizedutilitykit/operation_json.py
pypersonalizedutilitykit/pathSetting.py
pypersonalizedutilitykit/recursion.py
pypersonalizedutilitykit/touch_csv.py
pypersonalizedutilitykit/touch_file.py
pypersonalizedutilitykit/asserts/__init__.py
pypersonalizedutilitykit/asserts/assert_base.py
pypersonalizedutilitykit/asserts/res_assert.py
pypersonalizedutilitykit/database/__init__.py
pypersonalizedutilitykit/database/databaseScript/__init__.py
pypersonalizedutilitykit/database/databaseScript/xuanHu_databaseScript/__init__.py
pypersonalizedutilitykit/database/databaseScript/xuanHu_databaseScript/xuanHuDataBaseScript.py
pypersonalizedutilitykit/database/databaseScript/yunYaoKe_databaseScript/__init__.py
pypersonalizedutilitykit/database/database_design/__init__.py
pypersonalizedutilitykit/database/database_design/database_base.py
pypersonalizedutilitykit/database/database_design/database_insert.py
pypersonalizedutilitykit/database/database_design/database_listen.py
pypersonalizedutilitykit/database/database_design/database_table.py
pypersonalizedutilitykit/install_tool/__init__.py
pypersonalizedutilitykit/install_tool/install_requirements.py
pypersonalizedutilitykit/notify/__init__.py
pypersonalizedutilitykit/notify/aLiMail.py
pypersonalizedutilitykit/notify/notice.py
pypersonalizedutilitykit/notify/report.py
pypersonalizedutilitykit-0.0.1.dist-info/METADATA
pypersonalizedutilitykit-0.0.1.dist-info/WHEEL
pypersonalizedutilitykit-0.0.1.dist-info/top_level.txt
pypersonalizedutilitykit-0.0.1.dist-info/RECORD
