Metadata-Version: 2.1
Name: pypersonalizedutilitykit
Version: 0.0.1
Summary: Python常用代码小工具集锦
Home-page: https://gitee.com/Franklin_1/pypersonalizedtoolkit.git
Author: lyz
Author-email: 
License: GPLv3
Classifier: Programming Language :: Python :: 3
Classifier: License :: OSI Approved :: GNU General Public License v3 (GPLv3)
Classifier: Operating System :: OS Independent
Requires-Python: >=3.7
